mo_threads/__init__.py
mo_threads/busy_lock.py
mo_threads/commands.py
mo_threads/futures.py
mo_threads/lock.py
mo_threads/pools.py
mo_threads/processes.py
mo_threads/profile_utils.py
mo_threads/profiles.py
mo_threads/python.py
mo_threads/python_worker.py
mo_threads/queues.py
mo_threads/repeat.py
mo_threads/schedule.py
mo_threads/signals.py
mo_threads/threads.py
mo_threads/till.py
mo_threads-6.682.25104.dist-info/licenses/LICENSE
mo_threads-6.682.25104.dist-info/METADATA
mo_threads-6.682.25104.dist-info/WHEEL
mo_threads-6.682.25104.dist-info/top_level.txt
mo_threads-6.682.25104.dist-info/RECORD
