Metadata-Version: 2.4
Name: mo-threads
Version: 6.682.25104
Summary: More Threads! Simpler and faster threading.
Home-page: https://github.com/klahnakoski/mo-threads
Author: Kyle Lahnakoski
Author-email: kyle@lahnakoski.com
License: MPL 2.0
Classifier: Programming Language :: Python :: 3.8
Classifier: Programming Language :: Python :: 3.9
Classifier: Development Status :: 4 - Beta
Classifier: Topic :: Software Development :: Libraries
Classifier: Topic :: Software Development :: Libraries :: Python Modules
Classifier: License :: OSI Approved :: Mozilla Public License 2.0 (MPL 2.0)
Classifier: Programming Language :: Python :: 3.10
Classifier: Programming Language :: Python :: 3.11
Classifier: Programming Language :: Python :: 3.12
Classifier: Programming Language :: Python :: 3.13
License-File: LICENSE
Requires-Dist: mo-dots==10.678.25061
Requires-Dist: mo-future==7.678.25061
Requires-Dist: mo-logs==8.678.25061
Requires-Dist: mo-math==7.678.25061
Requires-Dist: mo-times==5.682.25104
Provides-Extra: tests
Requires-Dist: mo-testing>=8.674.25037; extra == "tests"
Requires-Dist: jx-python>=4.673.25037; extra == "tests"
Requires-Dist: psutil>=7.0.0; extra == "tests"
Requires-Dist: objgraph>=3.6.2; extra == "tests"
Requires-Dist: mo-files>=6.679.25061; extra == "tests"
Requires-Dist: mo-json>=6.679.25061; extra == "tests"
Requires-Dist: filelock>=3.16.1; extra == "tests"
Dynamic: author
Dynamic: author-email
Dynamic: classifier
Dynamic: description
Dynamic: description-content-type
Dynamic: home-page
Dynamic: license
Dynamic: license-file
Dynamic: provides-extra
Dynamic: requires-dist
Dynamic: summary
